apollo_io_mcp/__init__.py
apollo_io_mcp/schema.json
apollo_io_mcp/server.py
apollo_io_mcp-0.1.4.dist-info/LICENSE
apollo_io_mcp-0.1.4.dist-info/METADATA
apollo_io_mcp-0.1.4.dist-info/WHEEL
apollo_io_mcp-0.1.4.dist-info/entry_points.txt
apollo_io_mcp-0.1.4.dist-info/RECORD
